lily/__init__.py
lily/asynchronous/__init__.py
lily/asynchronous/backoff.py
lily/asynchronous/parallel.py
lily/asynchronous/task.py
lily/base/__init__.py
lily/base/access.py
lily/base/apps.py
lily/base/authorizer.py
lily/base/command.py
lily/base/commands.py
lily/base/context.py
lily/base/events.py
lily/base/input.py
lily/base/management/__init__.py
lily/base/management/commands/__init__.py
lily/base/management/commands/clear_examples.py
lily/base/meta.py
lily/base/models.py
lily/base/name.py
lily/base/output.py
lily/base/parsers.py
lily/base/serializers.py
lily/base/signature.py
lily/base/source.py
lily/base/test.py
lily/base/utils.py
lily/cli/__init__.py
lily/cli/base.makefile
lily/cli/cli.py
lily/cli/copier.py
lily/cli/logger.py
lily/conf/__init__.py
lily/conf/settings.py
lily/conf/urls.py
lily/conf/wsgi.py
lily/docs/__init__.py
lily/docs/management/__init__.py
lily/docs/management/commands/__init__.py
lily/docs/management/commands/render_angular.py
lily/docs/renderers/__init__.py
lily/docs/renderers/angular/__init__.py
lily/docs/renderers/angular/command.py
lily/docs/renderers/angular/domain.py
lily/docs/renderers/angular/interface.py
lily/docs/renderers/angular/renderer.py
lily/docs/renderers/angular/repo.py
lily/docs/renderers/angular/signature.py
lily/docs/renderers/angular/utils.py
lily/docs/renderers/markdown/__init__.py
lily/docs/renderers/markdown/base.md
lily/docs/renderers/markdown/renderer.py
lily/entrypoint/__init__.py
lily/entrypoint/apps.py
lily/entrypoint/base.py
lily/entrypoint/commands.py
lily/entrypoint/management/__init__.py
lily/entrypoint/management/commands/__init__.py
lily/entrypoint/management/commands/render_commands.py
lily/entrypoint/renderer.py
lily/entrypoint/schema.py
lily/entrypoint/serializers.py
lily/entrypoint/urls.py
lily/manage.py
lily/notebook/.ipynb_checkpoints/coder-typescript-stackblitz-checkpoint.ipynb
lily/notebook/.ipynb_checkpoints/command_context_for_dependencies_and_logging-checkpoint.ipynb
lily-3.0.1.dist-info/entry_points.txt
lily-3.0.1.dist-info/WHEEL
lily-3.0.1.dist-info/METADATA
lily-3.0.1.dist-info/RECORD
