Metadata-Version: 2.1
Name: lily
Version: 3.0.1
Summary: Lily MicroService Framework for Humans
Home-page: https://github.com/cosphere-org/lily
Keywords: lily,microservice,django,drf
Author: CoSphere Team
Author-email: contact@cosphere.org
Requires-Python: >=3.9.9,<3.10.0
Classifier: Programming Language :: Python :: 3
Classifier: Topic :: Software Development :: Libraries :: Python Modules
Requires-Dist: Django (>=3.2.11,<4.1.0)
Requires-Dist: PyYAML (>=6.0,<7.0)
Requires-Dist: django-bulk-update (>=2.2.0,<3.0.0)
Requires-Dist: django-click (>=2.3.0,<3.0.0)
Requires-Dist: djangorestframework (>=3.13.1,<4.0.0)
Requires-Dist: inflect (>=5.3.0,<6.0.0)
Requires-Dist: itsdangerous (>=2.0.1,<3.0.0)
Requires-Dist: jsonschema (>=4.3.1,<5.0.0)
Requires-Dist: langid (>=1.1.6,<2.0.0)
Requires-Dist: orjson (>=3.6.5,<4.0.0)
Requires-Dist: psycopg2-binary (>=2.9.2,<3.0.0)
Requires-Dist: pytz (>=2021.3,<2022.0)
Requires-Dist: requests (>=2.26.0,<3.0.0)
Requires-Dist: trans (>=2.1.0,<3.0.0)
Project-URL: Repository, https://github.com/cosphere-org/lily
